pysigrok_raspberrypi_pico.py
pysigrok_hardware_raspberrypi_pico-0.3.1.dist-info/entry_points.txt
pysigrok_hardware_raspberrypi_pico-0.3.1.dist-info/LICENSE
pysigrok_hardware_raspberrypi_pico-0.3.1.dist-info/WHEEL
pysigrok_hardware_raspberrypi_pico-0.3.1.dist-info/METADATA
pysigrok_hardware_raspberrypi_pico-0.3.1.dist-info/RECORD
